Metadata-Version: 2.1
Name: heroescli
Version: 1.0.1
Summary: Get Awesome Random Heroes names in CLI!
Home-page: https://yoginth.gitlab.io
Author: Yoginth
Author-email: yoginth@zoho.com
License: UNKNOWN
Project-URL: Patreon, https://www.patreon.com/yoginth
Project-URL: Source, https://gitlab.com/yoginth/heroescli
Platform: UNKNOWN
Classifier: Programming Language :: Python
Classifier: Natural Language :: English
Classifier: Environment :: Console
Classifier: Operating System :: OS Independent
Classifier: Intended Audience :: End Users/Desktop
Classifier: License :: OSI Approved :: MIT License
